LAB-04/decod_bcd.v
module decod_bcd (

    //Input
    input wire[3:0] count,
    
    //Output
    output reg[6:0] seg_count
);
    
    always @ * begin
    	case (count)
    	4'b0000 : seg_count = 7'b0000001;
    	4'b0001 : seg_count = 7'b1001111;
    	4'b0010 : seg_count = 7'b0010010;
    	4'b0011 : seg_count = 7'b0000110;
    	4'b0100 : seg_count = 7'b1001100;
    	4'b0101 : seg_count = 7'b0100100;
    	4'b0110 : seg_count = 7'b0100000;
    	4'b0111 : seg_count = 7'b0001111;
    	4'b1000 : seg_count = 7'b0000000;
    	4'b1001 : seg_count = 7'b0000100;
    	4'b1010 : seg_count = 7'b0001000;
    	4'b1011 : seg_count = 7'b1100000;
    	4'b1100 : seg_count = 7'b0110001;
    	4'b1101 : seg_count = 7'b1000010;
    	4'b1110 : seg_count = 7'b0110000;
    	4'b1111 : seg_count = 7'b0111000;
    	endcase
    end
endmodule

LAB-04/frequency_divider.v
module frequency_divider (

    // Inputs
    input clk,
    input rst_btn,

    // Outputs
    output reg[3:0] out_clk
);
    wire rst;
    reg[31:0] count;
    localparam [31:0] max_count = (12000000) - 1;

    // Reset is the inverse of the reset button
    assign rst = ~rst_btn;

    // Clock divider
    always @(posedge clk or posedge rst) begin
        if (rst) begin
            out_clk <= 4'b0;
            count <= 32'b0;
        end
        else if (count == max_count) begin
            count <= 32'b0;
            out_clk <= out_clk + 1'b1;
        end
        else begin
            count <= count + 1;
        end
    end

endmodule

LAB-04/top_level.v
`include "frequency_divider.v"
`include "decod_bcd.v"


module top_level(
	//Inputs
	input clk,
	input rst_btn,
	
	//Output
	output wire[6:0] seg_count
);
	wire[3:0] out_clk;
	frequency_divider inst1(clk, rst_btn, out_clk);
	decod_bcd inst2(out_clk, seg_count);
endmodule

LAB-04/top_level_tb.v
`timescale 10ns/1ps
`include "top_level.v"

module top_level_tb ;

    output reg clk, rst;
    input wire[6:0] seg_count;

    top_level uut(clk, rst, seg_count);
    
    initial
        clk = 1'b0 ;
    
    always
        #1 clk = ~clk;
    
    initial begin
        $monitor($time,"clk = %b, rst = %b, seg_count = %b", clk, rst, seg_count);
        rst = 0;
        #1 rst = 1;
        #31 $finish;
    end

    initial begin
        $dumpfile ("top_level_tb.vcd");
        $dumpvars (0, top_level_tb);
    end

endmodule

LAB-04/top_level_tb.vcd
$date
	Thu Sep 15 11:49:42 2022
$end
$version
	Icarus Verilog
$end
$timescale
	1ps
$end
$scope module top_level_tb $end
$var wire 7 ! seg_count [6:0] $end
$var reg 1 " clk $end
$var reg 1 # rst $end
$scope module uut $end
$var wire 1 " clk $end
$var wire 1 # rst_btn $end
$var wire 7 $ seg_count [6:0] $end
$var wire 4 % out_clk [3:0] $end
$scope module inst1 $end
$var wire 1 " clk $end
$var wire 1 & rst $end
$var wire 1 # rst_btn $end
$var reg 32 ' count [31:0] $end
$var reg 4 ( out_clk [3:0] $end
$upscope $end
$scope module inst2 $end
$var wire 4 ) count [3:0] $end
$var reg 7 * seg_count [6:0] $end
$upscope $end
$upscope $end
$upscope $end
$enddefinitions $end
#0
$dumpvars
b1 *
b0 )
b0 (
b0 '
1&
b0 %
b1 $
0#
0"
b1 !
$end
#10000
0&
1#
1"
#20000
0"
#30000
b1 '
1"
#40000
0"
#50000
b10 '
1"
#60000
0"
#70000
b11 '
1"
#80000
0"
#90000
b100 '
1"
#100000
0"
#110000
b101 '
1"
#120000
0"
#130000
b110 '
1"
#140000
0"
#150000
b111 '
1"
#160000
0"
#170000
b1000 '
1"
#180000
0"
#190000
b1001 '
1"
#200000
0"
#210000
b1010 '
1"
#220000
0"
#230000
b1011 '
1"
#240000
0"
#250000
b1100 '
1"
#260000
0"
#270000
b1101 '
1"
#280000
0"
#290000
b1110 '
1"
#300000
0"
#310000
b1111 '
1"
