LAB-01/blink.v
module blink ( input CLK ,
		output LED
);

 reg [25:0] counter ;

 assign LED = ~ counter [0];

 initial begin
 counter = 0;
 end

 always @ ( posedge CLK )
 begin
 counter <= counter + 1;
 end

 endmodule

LAB-01/blink_tb.v

`timescale 10ns/1ps

module blink_tb;
    
     reg CLK;
     wire LED;


     blink blink_tb(CLK, LED);
     
     initial
          CLK = 1'b0;

     always
          #1 CLK = ~CLK;

     initial begin
          $monitor($time,"CLK = %b, LED = %b", CLK, LED);
          #31 $finish;
     end
     
     initial begin
          $dumpfile ("blink_tb.vcd");
          $dumpvars (0, blink_tb);
     end

endmodule

LAB-01/blink_tb.vcd
$date
	Thu Aug  4 14:50:21 2022
$end
$version
	Icarus Verilog
$end
$timescale
	1ps
$end
$scope module blink_tb $end
$scope module blink_tb $end
$var wire 1 ! CLK $end
$var wire 1 " LED $end
$var reg 26 # counter [25:0] $end
$upscope $end
$upscope $end
$enddefinitions $end
#0
$dumpvars
b0 #
1"
0!
$end
#10000
0"
b1 #
1!
#20000
0!
#30000
1"
b10 #
1!
#40000
0!
#50000
0"
b11 #
1!
#60000
0!
#70000
1"
b100 #
1!
#80000
0!
#90000
0"
b101 #
1!
#100000
0!
#110000
1"
b110 #
1!
#120000
0!
#130000
0"
b111 #
1!
#140000
0!
#150000
1"
b1000 #
1!
#160000
0!
#170000
0"
b1001 #
1!
#180000
0!
#190000
1"
b1010 #
1!
#200000
0!
#210000
0"
b1011 #
1!
#220000
0!
#230000
1"
b1100 #
1!
#240000
0!
#250000
0"
b1101 #
1!
#260000
0!
#270000
1"
b1110 #
1!
#280000
0!
#290000
0"
b1111 #
1!
#300000
0!
#310000
1"
b10000 #
1!
