LAB-05/mux_8_1.v
module mux_8_1 (
    // Inputs
    input [3:0] i0, i1, i2, i3, i4, i5, i6, i7,
    input [2:0] s,
    // Outputs
    output [3:0] y
);
    assign y[3] = i0[3] & ~s[0] & ~s[1]  & ~s[2]   |
                  i1[3] & s[0]  & ~s[1]  & ~s[2]   |
                  i2[3] & ~s[0] & s[1]   & ~s[2]   |
                  i3[3] & s[0]  & s[1]   &  ~s[2]  |
                  i4[3] & ~s[0] & ~s[1]  &  s[2]   |
                  i5[3] & s[0]  & ~s[1]  &  s[2]   |
                  i6[3] & ~s[0] & s[1]   &  s[2]   |
                  i7[3] & s[0]  & s[1]   &  s[2];
                  

    assign y[2] = i0[2] & ~s[0] & ~s[1]  & ~s[2]   |
                  i1[2] & s[0]  & ~s[1]  & ~s[2]   |
                  i2[2] & ~s[0] & s[1]   & ~s[2]   |
                  i3[2] & s[0]  & s[1]   &  ~s[2]  |
                  i4[2] & ~s[0] & ~s[1]  &  s[2]   |
                  i5[2] & s[0]  & ~s[1]  &  s[2]   |
                  i6[2] & ~s[0] & s[1]   &  s[2]   |
                  i7[2] & s[0]  & s[1]   &  s[2];

    assign y[1] = i0[1] & ~s[0] & ~s[1]  & ~s[2]   |
                  i1[1] & s[0]  & ~s[1]  & ~s[2]   |
                  i2[1] & ~s[0] & s[1]   & ~s[2]   |
                  i3[1] & s[0]  & s[1]   &  ~s[2]  |
                  i4[1] & ~s[0] & ~s[1]  &  s[2]   |
                  i5[1] & s[0]  & ~s[1]  &  s[2]   |
                  i6[1] & ~s[0] & s[1]   &  s[2]   |
                  i7[1] & s[0]  & s[1]   &  s[2];

    assign y[0] = i0[0] & ~s[0] & ~s[1]  & ~s[2]   |
                  i1[0] & s[0]  & ~s[1]  & ~s[2]   |
                  i2[0] & ~s[0] & s[1]   & ~s[2]   |
                  i3[0] & s[0]  & s[1]   &  ~s[2]  |
                  i4[0] & ~s[0] & ~s[1]  &  s[2]   |
                  i5[0] & s[0]  & ~s[1]  &  s[2]   |
                  i6[0] & ~s[0] & s[1]   &  s[2]   |
                  i7[0] & s[0]  & s[1]   &  s[2];
endmodule

LAB-05/alu.v
`include "mux_8_1.v"
module alu (
    input [3:0] src_a, src_b,
    input [2:0] operation,
    output [3:0] alu_result,
    output zero_flag
);

    wire [3:0] opand,opor,opplus,opsl,opminus,opsr,opAltB,opXOR;
    
    assign opand=src_a & src_b;
    assign opor=src_a | src_b;
    assign opplus=src_a + src_b;
    assign opsl=src_a << src_b;
    assign opminus=src_a - src_b;
    assign opsr=src_a >> src_b;
    assign opAltB=src_a < src_b;
    assign opXOR=src_a ^ src_b;
    mux_8_1 mux (opand,opor,opplus,opsl,opminus,opsr,opAltB,opXOR,operation,alu_result);

    assign zero_flag = alu_result ? 0:1;

endmodule

LAB-05/alu_tb.v
`include "alu.v"

module alu_tb ();

    parameter DATA_WIDTH = 4;
    parameter OPCODE_LENGTH = 3;

    reg [DATA_WIDTH - 1:0] A;
    reg [DATA_WIDTH - 1:0] B;
    reg [OPCODE_LENGTH - 1:0] OP;

    wire [DATA_WIDTH - 1:0] RESULT ;
    wire F_ZERO;

    alu uut (   .src_a(A),
                .src_b(B),
                .operation(OP),
                .alu_result(RESULT),
                .zero_flag(F_ZERO)
    );

    initial begin
        A = 1; B = 2; OP = 4'b0000; #1
        A = 1; B = 2; OP = 4'b0001; #1
        A = 1; B = 2; OP = 4'b0010; #1
        A = 1; B = 2; OP = 4'b0011; #1
        A = 1; B = 2; OP = 4'b0100; #1
        A = 4; B = 2; OP = 4'b0101; #1
        A = 3; B = 2; OP = 4'b0110; #1
        A = 2; B = 2; OP = 4'b0111; #1;
    end
	initial begin
	    $dumpfile ("alu_tb.vcd");
	    $dumpvars (0, alu_tb);
	end

endmodule

LAB-05/alu_tb.vcd
$date
	Thu Oct  6 11:31:14 2022
$end
$version
	Icarus Verilog
$end
$timescale
	1s
$end
$scope module alu_tb $end
$var wire 4 ! RESULT [3:0] $end
$var wire 1 " F_ZERO $end
$var reg 4 # A [3:0] $end
$var reg 4 $ B [3:0] $end
$var reg 3 % OP [2:0] $end
$scope module uut $end
$var wire 4 & opXOR [3:0] $end
$var wire 4 ' opand [3:0] $end
$var wire 3 ( operation [2:0] $end
$var wire 4 ) opor [3:0] $end
$var wire 4 * src_a [3:0] $end
$var wire 4 + src_b [3:0] $end
$var wire 1 " zero_flag $end
$var wire 4 , opsr [3:0] $end
$var wire 4 - opsl [3:0] $end
$var wire 4 . opplus [3:0] $end
$var wire 4 / opminus [3:0] $end
$var wire 4 0 opAltB [3:0] $end
$var wire 4 1 alu_result [3:0] $end
$scope module mux $end
$var wire 4 2 i0 [3:0] $end
$var wire 4 3 i1 [3:0] $end
$var wire 4 4 i2 [3:0] $end
$var wire 4 5 i3 [3:0] $end
$var wire 4 6 i4 [3:0] $end
$var wire 4 7 i5 [3:0] $end
$var wire 4 8 i6 [3:0] $end
$var wire 4 9 i7 [3:0] $end
$var wire 3 : s [2:0] $end
$var wire 4 ; y [3:0] $end
$upscope $end
$upscope $end
$upscope $end
$enddefinitions $end
#0
$dumpvars
b0 ;
b0 :
b11 9
b1 8
b0 7
b1111 6
b100 5
b11 4
b11 3
b0 2
b0 1
b1 0
b1111 /
b11 .
b100 -
b0 ,
b10 +
b1 *
b11 )
b0 (
b0 '
b11 &
b0 %
b10 $
b1 #
1"
b0 !
$end
#1
0"
b11 !
b11 1
b11 ;
b1 %
b1 (
b1 :
#2
b11 !
b11 1
b11 ;
b10 %
b10 (
b10 :
#3
b100 !
b100 1
b100 ;
b11 %
b11 (
b11 :
#4
b1111 !
b1111 1
b1111 ;
b100 %
b100 (
b100 :
#5
b1 !
b1 1
b1 ;
b110 )
b110 3
b110 &
b110 9
b101 %
b101 (
b101 :
b110 .
b110 4
b0 -
b0 5
b10 /
b10 6
b1 ,
b1 7
b0 0
b0 8
b100 #
b100 *
#6
1"
b0 !
b0 1
b0 ;
b10 '
b10 2
b11 )
b11 3
b1 &
b1 9
b110 %
b110 (
b110 :
b101 .
b101 4
b1100 -
b1100 5
b1 /
b1 6
b0 ,
b0 7
b11 #
b11 *
#7
b10 )
b10 3
b0 &
b0 9
b111 %
b111 (
b111 :
b100 .
b100 4
b1000 -
b1000 5
b0 /
b0 6
b10 #
b10 *
