LAB-05/mux_8_1.v
module mux_8_1 (
    // Inputs
    input [3:0] i0, i1, i2, i3, i4, i5, i6, i7,
    input [2:0] s,
    // Outputs
    output [3:0] y
);
    assign y[3] = i0[3] & ~s[0] & ~s[1]  & ~s[2]   |
                  i1[3] & s[0]  & ~s[1]  & ~s[2]   |
                  i2[3] & ~s[0] & s[1]   & ~s[2]   |
                  i3[3] & s[0]  & s[1]   &  ~s[2]  |
                  i4[3] & ~s[0] & ~s[1]  &  s[2]   |
                  i5[3] & s[0]  & ~s[1]  &  s[2]   |
                  i6[3] & ~s[0] & s[1]   &  s[2]   |
                  i7[3] & s[0]  & s[1]   &  s[2];
                  

    assign y[2] = i0[2] & ~s[0] & ~s[1]  & ~s[2]   |
                  i1[2] & s[0]  & ~s[1]  & ~s[2]   |
                  i2[2] & ~s[0] & s[1]   & ~s[2]   |
                  i3[2] & s[0]  & s[1]   &  ~s[2]  |
                  i4[2] & ~s[0] & ~s[1]  &  s[2]   |
                  i5[2] & s[0]  & ~s[1]  &  s[2]   |
                  i6[2] & ~s[0] & s[1]   &  s[2]   |
                  i7[2] & s[0]  & s[1]   &  s[2];

    assign y[1] = i0[1] & ~s[0] & ~s[1]  & ~s[2]   |
                  i1[1] & s[0]  & ~s[1]  & ~s[2]   |
                  i2[1] & ~s[0] & s[1]   & ~s[2]   |
                  i3[1] & s[0]  & s[1]   &  ~s[2]  |
                  i4[1] & ~s[0] & ~s[1]  &  s[2]   |
                  i5[1] & s[0]  & ~s[1]  &  s[2]   |
                  i6[1] & ~s[0] & s[1]   &  s[2]   |
                  i7[1] & s[0]  & s[1]   &  s[2];

    assign y[0] = i0[0] & ~s[0] & ~s[1]  & ~s[2]   |
                  i1[0] & s[0]  & ~s[1]  & ~s[2]   |
                  i2[0] & ~s[0] & s[1]   & ~s[2]   |
                  i3[0] & s[0]  & s[1]   &  ~s[2]  |
                  i4[0] & ~s[0] & ~s[1]  &  s[2]   |
                  i5[0] & s[0]  & ~s[1]  &  s[2]   |
                  i6[0] & ~s[0] & s[1]   &  s[2]   |
                  i7[0] & s[0]  & s[1]   &  s[2];
endmodule

LAB-05/mux_8_1_tb.v
`include "mux_8_1.v"
`timescale 1 ns /1 ps // time unit / simulation precision

module mux_8_1_tb ;

	reg [3:0] i0, i1, i2, i3, i4, i5, i6, i7 ;
	reg [2:0] S ;
	wire [3:0] Y ;

 	mux_8_1 uut ( i0, i1, i2, i3, i4, i5, i6, i7, S , Y );

 	initial begin
 		$dumpfile ("mux_8_1_tb.vcd");
 		$dumpvars (0 , mux_8_1_tb );
 	end

 	initial begin
 		i0 = 4; i1 = 8; i2 = 1; i3 = 15; i4 = 3; i5 = 7; i6 = 0; i7 = 14; S = 0; #1
 		i0 = 4; i1 = 8; i2 = 1; i3 = 15; i4 = 3; i5 = 7; i6 = 0; i7 = 14; S = 1; #1
 		i0 = 4; i1 = 8; i2 = 1; i3 = 15; i4 = 3; i5 = 7; i6 = 0; i7 = 14; S = 2; #1
 		i0 = 4; i1 = 8; i2 = 1; i3 = 15; i4 = 3; i5 = 7; i6 = 0; i7 = 14; S = 3; #1
 		i0 = 4; i1 = 8; i2 = 1; i3 = 15; i4 = 3; i5 = 7; i6 = 0; i7 = 14; S = 4; #1
 		i0 = 4; i1 = 8; i2 = 1; i3 = 15; i4 = 3; i5 = 7; i6 = 0; i7 = 14; S = 5; #1
 		i0 = 4; i1 = 8; i2 = 1; i3 = 15; i4 = 3; i5 = 7; i6 = 0; i7 = 14; S = 6; #1
 		i0 = 4; i1 = 8; i2 = 1; i3 = 15; i4 = 3; i5 = 7; i6 = 0; i7 = 14; S = 7; #1;
 		
 	end

 endmodule

LAB-05/mux_8_1_tb.vcd
$date
	Thu Oct  6 11:05:11 2022
$end
$version
	Icarus Verilog
$end
$timescale
	1ps
$end
$scope module mux_8_1_tb $end
$var wire 4 ! Y [3:0] $end
$var reg 3 " S [2:0] $end
$var reg 4 # i0 [3:0] $end
$var reg 4 $ i1 [3:0] $end
$var reg 4 % i2 [3:0] $end
$var reg 4 & i3 [3:0] $end
$var reg 4 ' i4 [3:0] $end
$var reg 4 ( i5 [3:0] $end
$var reg 4 ) i6 [3:0] $end
$var reg 4 * i7 [3:0] $end
$scope module uut $end
$var wire 4 + i0 [3:0] $end
$var wire 4 , i1 [3:0] $end
$var wire 4 - i2 [3:0] $end
$var wire 4 . i3 [3:0] $end
$var wire 4 / i4 [3:0] $end
$var wire 4 0 i5 [3:0] $end
$var wire 4 1 i6 [3:0] $end
$var wire 4 2 i7 [3:0] $end
$var wire 3 3 s [2:0] $end
$var wire 4 4 y [3:0] $end
$upscope $end
$upscope $end
$enddefinitions $end
#0
$dumpvars
b100 4
b0 3
b1110 2
b0 1
b111 0
b11 /
b1111 .
b1 -
b1000 ,
b100 +
b1110 *
b0 )
b111 (
b11 '
b1111 &
b1 %
b1000 $
b100 #
b0 "
b100 !
$end
#1000
b1000 !
b1000 4
b1 "
b1 3
#2000
b1 !
b1 4
b10 "
b10 3
#3000
b1111 !
b1111 4
b11 "
b11 3
#4000
b11 !
b11 4
b100 "
b100 3
#5000
b111 !
b111 4
b101 "
b101 3
#6000
b0 !
b0 4
b110 "
b110 3
#7000
b1110 !
b1110 4
b111 "
b111 3
